{
  "author": "ekky.pertamini",
  "title": "Angkutan Umum Jakarta - Bekasi",
  "description": "Ada ga angkutan yang langsung Jakarta - Bekasi? Mau coba jalan jalan lucu di Bekasi ehehehe makasi yaa",
  "categories": [
    "JAKARTA",
    "BEKASI"
  ],
  "answers": [
    {
      "author": "arum.djeram",
      "description": "Ini daftar angkutannya: <br>Angkutan Perbatasan Terintegrasi Busway (APTB) 07 Tanah Abang – Bekasi<br>Rutenya : Tanah Abang – Jalan M.H. Thamrin – Bundaran Hotel Indonesia (HI) – Jalan Jenderal Sudirman – Dukuh Atas – Setiabudi – Karet – Bendungan Hilir – Semanggi – Jalan Gatot Subroto – Kuningan – Pancoran – Jalan M.T. Haryono – Jalan Tol Cikampek – Bekasi Barat – Jalan Cut Meutia Bekasi – Terminal Bekasi<br><br>Trus lainnya itu ada:<br>Mayasari Bakti AC05 : Blok M – Bekasi<br>Mayasari Bakti AC24 : Senen – Bekasi (Tol Timur)<br>Mayasari Bakti AC25 : Tanjung Priok – Bekasi (Tol Barat)<br>Mayasari Bakti AC26 : Grogol – Bekasi (Tol Timur)<br>Mayasari Bakti AC28 : Blok M – Bekasi (Tol Timur)<br>Mayasari Bakti AC29 : Kalideres – Bekasi (Tol Barat)<br>Mayasari Bakti AC52 : Tanah Abang – Bekasi (Tol Timur)<br>Mayasari Bakti AC132 : Lebak Bulus – Bekasi (Tol Timur) via TOL Cikunir"
    }
  ]
}
